Metadata-Version: 2.1
Name: odoo8-addon-analytic-partner-hr-timesheet
Version: 8.0.1.0.0.99.dev22
Summary: Classify HR activities by partner
Home-page: http://www.antiun.com
Author: Antiun Ingeniería S.L., Serv. Tecnol. Avanzados - Pedro M. Baeza, Odoo Community Association (OCA)
Author-email: support@odoo-community.org
License: AGPL-3
Platform: UNKNOWN
Classifier: Programming Language :: Python
Classifier: Framework :: Odoo
Classifier: License :: OSI Approved :: GNU Affero General Public License v3
Requires-Python: ~=2.7
Requires-Dist: odoo8-addon-analytic-partner
Requires-Dist: odoo (<9.0a,>=8.0a)
